Massaki01/Massaki01.py
Massaki01/__init__.py
Massaki01-0.1.dist-info/LICENSE.txt
Massaki01-0.1.dist-info/METADATA
Massaki01-0.1.dist-info/WHEEL
Massaki01-0.1.dist-info/top_level.txt
Massaki01-0.1.dist-info/RECORD
